onekey_client/__init__.py
onekey_client/cli/__init__.py
onekey_client/cli/ci.py
onekey_client/cli/cli.py
onekey_client/cli/firmware_upload.py
onekey_client/cli/misc.py
onekey_client/client.py
onekey_client/errors.py
onekey_client/keys/__init__.py
onekey_client/keys/ca.pem
onekey_client/models.py
onekey_client/queries/__init__.py
onekey_client/queries/compare_firmware.graphql
onekey_client/queries/create_firmware_upload.graphql
onekey_client/queries/get_analysis_configurations.graphql
onekey_client/queries/get_firmware_latest_analysis_state.graphql
onekey_client/queries/get_firmware_latest_results.graphql
onekey_client/queries/get_product_groups.graphql
onekey_client/queries/get_same_product_firmwares.graphql
onekey_client/queries/get_self.graphql
onekey_client/queries/utils.py
onekey_client-2.3.0.dist-info/LICENSE
onekey_client-2.3.0.dist-info/METADATA
onekey_client-2.3.0.dist-info/WHEEL
onekey_client-2.3.0.dist-info/entry_points.txt
onekey_client-2.3.0.dist-info/RECORD
