Metadata-Version: 2.1
Name: onekey_client
Version: 2.3.0
Summary: ONEKEY API client
Home-page: https://www.onekey.com/
License: MIT
Keywords: iot,security,firmware,analysis
Author: ONEKEY
Author-email: support@onekey.com
Requires-Python: >=3.8.0,<4.0.0
Classifier: Development Status :: 4 - Beta
Classifier: Environment :: Console
Classifier: License :: OSI Approved :: MIT License
Classifier: Operating System :: OS Independent
Classifier: Programming Language :: Python :: 3
Classifier: Programming Language :: Python :: 3.8
Classifier: Programming Language :: Python :: 3.9
Classifier: Programming Language :: Python :: 3.10
Classifier: Programming Language :: Python :: 3.11
Classifier: Programming Language :: Python :: 3.12
Classifier: Programming Language :: Python :: 3 :: Only
Classifier: Topic :: Security
Requires-Dist: Authlib (>=0.15.3,<0.16.0)
Requires-Dist: click (>=8.1.3,<9.0.0)
Requires-Dist: httpx (==0.23.0)
Requires-Dist: importlib-resources (>=5.1.2,<6.0.0)
Requires-Dist: junit-xml (>=1.9,<2.0)
Requires-Dist: pydantic (==1.8.2)
Project-URL: Bug Tracker, https://github.com/onekey-sec/python-client/issues
Project-URL: GitHub, https://github.com/onekey-sec/python-client
